pygame_cards/__init__.py
pygame_cards/abstract.py
pygame_cards/back.py
pygame_cards/board.py
pygame_cards/classics.py
pygame_cards/constants.py
pygame_cards/deck.py
pygame_cards/defaults.py
pygame_cards/effects.py
pygame_cards/events.py
pygame_cards/game.py
pygame_cards/hands.py
pygame_cards/manager.py
pygame_cards/set.py
pygame_cards/tokens.py
pygame_cards/utils.py
"pygame_cards/images/DALL·E 2022-08-25 13.56.20 - funny happy python, digital art.png"
pygame_cards/images/DEFAULT_CARDBACK.png
pygame_cards/images/__init__.py
pygame_cards/io/__init__.py
pygame_cards/io/__main__.py
pygame_cards/io/json.py
pygame_cards/io/utils.py
pygame_cards/server/__init__.py
pygame_cards/server/client.py
pygame_cards/server/events.py
pygame_cards/server/host.py
pygame_cards/server/player.py
pygame_cards/server/remote_players.py
pygame_cards-0.2.0.dist-info/licenses/LICENSE
pygame_cards-0.2.0.dist-info/METADATA
pygame_cards-0.2.0.dist-info/WHEEL
pygame_cards-0.2.0.dist-info/top_level.txt
pygame_cards-0.2.0.dist-info/RECORD
