Metadata-Version: 2.4
Name: pygame_cards
Version: 0.2.0
Summary: Framework for simple cards games powered by Pygame
Author-email: Lionel42 <lionel@sciencegames.ch>
License: MIT License
Project-URL: Homepage, https://github.com/ScienceGamez/pygame_cards
Project-URL: Bug Tracker, https://github.com/ScienceGamez/pygame_cards/issues
Project-URL: Documentation, https://pygame-cards.readthedocs.io/en/latest/
Classifier: Programming Language :: Python :: 3
Classifier: License :: OSI Approved :: MIT License
Classifier: Operating System :: OS Independent
Requires-Python: >=3.10
License-File: LICENSE
Requires-Dist: pygame
Requires-Dist: pygame_emojis>=0.2
Requires-Dist: numpy
Provides-Extra: doc
Requires-Dist: sphinx; extra == "doc"
Requires-Dist: furo; extra == "doc"
Dynamic: license-file
